scu_api/__init__.py
scu_api/constant.py
scu_api/logger.py
scu_api/spider.py
scu_api/student.py
scu_api/u_student.py
scu_api/utils.py
scu_api-0.0.3.dist-info/LICENSE
scu_api-0.0.3.dist-info/METADATA
scu_api-0.0.3.dist-info/WHEEL
scu_api-0.0.3.dist-info/top_level.txt
scu_api-0.0.3.dist-info/RECORD
