Metadata-Version: 2.1
Name: scu-api
Version: 0.0.3
Summary: An api provide for Sichuan University
Home-page: https://github.com/hx-w/scu-api
Author: CarOL
Author-email: herixth@gmail.com
License: GNU General Public License v3.0
Requires-Python: >=3.6
License-File: LICENSE
Requires-Dist: requests (==2.25.1)
Requires-Dist: ujson
